Metadata-Version: 1.0
Name: dirly
Version: 0.1
Summary: Quickly map your function to every file in a directory (verb: to dirl).
Home-page: https://github.com/SharifElfouly/dirly
Author: Sharif Elfouly
Author-email: selfouly@gmail.com
License: MIT
Platform: UNKNOWN
